discord/ext/audiorec/__init__.py
discord/ext/audiorec/ffi.cpython-39-darwin.so
discord/ext/audiorec/voice_client.py
discord_ext_audiorec-0.1.6.dist-info/LICENSE
discord_ext_audiorec-0.1.6.dist-info/METADATA
discord_ext_audiorec-0.1.6.dist-info/WHEEL
discord_ext_audiorec-0.1.6.dist-info/top_level.txt
discord_ext_audiorec-0.1.6.dist-info/RECORD
